mtlbs/__init__.py
mtlbs/mtlbs.py
mtlbs-0.0.6.dist-info/METADATA
mtlbs-0.0.6.dist-info/WHEEL
mtlbs-0.0.6.dist-info/top_level.txt
mtlbs-0.0.6.dist-info/RECORD
